sbclassifier/__init__.py
sbclassifier/chi2.py
sbclassifier/classifier.py
sbclassifier/histogram.py
sbclassifier/tokenizer.py
sbclassifier-0.1.1.dist-info/LICENSE.txt
sbclassifier-0.1.1.dist-info/METADATA
sbclassifier-0.1.1.dist-info/WHEEL
sbclassifier-0.1.1.dist-info/top_level.txt
sbclassifier-0.1.1.dist-info/RECORD
