Metadata-Version: 2.1
Name: sbclassifier
Version: 0.1.1
Summary: The bayesian spam classifier from SpamBayes
Home-page: https://sr.ht/~olly/sbclassifier/
Author: Oliver Cope
Author-email: oliver@redgecko.org
License: PSF
Keywords: bayes bayesian spambayes classifier spam
Platform: UNKNOWN
Classifier: Development Status :: 4 - Beta
Classifier: Intended Audience :: Developers
Classifier: License :: OSI Approved :: Python Software Foundation License
Classifier: Operating System :: OS Independent
Classifier: Topic :: Software Development
Classifier: Topic :: Software Development :: Libraries
Classifier: Topic :: Text Processing :: Filters
Classifier: Programming Language :: Python :: 3
License-File: LICENSE.txt
